{"3900222":[20,"松本市","入山辺"],"3900301":[20,"松本市","稲倉"],"3900302":[20,"松本市","三才山"],"3900303":[20,"松本市","浅間温泉"],"3900304":[20,"松本市","大村"],"3900305":[20,"松本市","惣社"],"3900306":[20,"松本市","南浅間"],"3900311":[20,"松本市","水汲"],"3900312":[20,"松本市","岡田松岡"],"3900313":[20,"松本市","岡田下岡田"],"3900314":[20,"松本市","岡田伊深"],"3900315":[20,"松本市","岡田町"],"3900316":[20,"松本市","原"],"3900317":[20,"松本市","洞"],"3900801":[20,"松本市","美須々"],"3900802":[20,"松本市","旭"],"3900803":[20,"松本市","元町"],"3900804":[20,"松本市","横田"],"3900805":[20,"松本市","清水"],"3900806":[20,"松本市","女鳥羽"],"3900807":[20,"松本市","城東"],"3900811":[20,"松本市","中央"],"3900812":[20,"松本市","県"],"3900813":[20,"松本市","埋橋"],"3900814":[20,"松本市","本庄"],"3900815":[20,"松本市","深志"],"3900816":[20,"松本市","中条"],"3900817":[20,"松本市","巾上"],"3900821":[20,"松本市","筑摩"],"3900822":[20,"松本市","神田"],"3900823":[20,"松本市","中山"],"3900824":[20,"松本市","中山台"],"3900825":[20,"松本市","並柳"],"3900826":[20,"松本市","出川町"],"3900827":[20,"松本市","出川"],"3900828":[20,"松本市","庄内"],"3900831":[20,"松本市","井川城"],"3900832":[20,"松本市","南松本"],"3900833":[20,"松本市","双葉"],"3900834":[20,"松本市","高宮中"],"3900835":[20,"松本市","高宮東"],"3900836":[20,"松本市","高宮北"],"3900837":[20,"松本市","鎌田"],"3900841":[20,"松本市","渚"],"3900842":[20,"松本市","征矢野"],"3900843":[20,"松本市","高宮南"],"3900844":[20,"松本市","高宮西"],"3900845":[20,"松本市","石芝"],"3900846":[20,"松本市","南原"],"3900847":[20,"松本市","笹部"],"3900848":[20,"松本市","両島"],"3900851":[20,"松本市","島内"],"3900852":[20,"松本市","島立"],"3900861":[20,"松本市","蟻ケ崎"],"3900862":[20,"松本市","宮渕"],"3900863":[20,"松本市","白板"],"3900864":[20,"松本市","宮渕本村"],"3900865":[20,"松本市","新橋"],"3900866":[20,"松本市","城山"],"3900867":[20,"松本市","蟻ケ崎台"],"3900871":[20,"松本市","桐"],"3900872":[20,"松本市","北深志"],"3900873":[20,"松本市","丸の内"],"3900874":[20,"松本市","大手"],"3900875":[20,"松本市","城西"],"3900876":[20,"松本市","開智"],"3900877":[20,"松本市","沢村"],"3901100":[20,"東筑摩郡朝日村",""],"3901101":[20,"東筑摩郡朝日村","西洗馬"],"3901102":[20,"東筑摩郡朝日村","小野沢"],"3901103":[20,"東筑摩郡朝日村","針尾"],"3901104":[20,"東筑摩郡朝日村","古見"],"3901131":[20,"松本市","今井"],"3901132":[20,"松本市","空港東"],"3901241":[20,"松本市","新村"],"3901242":[20,"松本市","和田"],"3901243":[20,"松本市","神林"],"3901301":[20,"東筑摩郡山形村","山形村一円"],"3901401":[20,"松本市","波田"],"3901501":[20,"松本市","安曇"],"3901502":[20,"松本市","安曇"],"3901503":[20,"松本市","安曇"],"3901504":[20,"松本市","安曇"],"3901506":[20,"松本市","安曇"],"3901507":[20,"松本市","安曇"],"3901511":[20,"松本市","安曇"],"3901512":[20,"松本市","安曇"],"3901513":[20,"松本市","安曇"],"3901514":[20,"松本市","安曇"],"3901515":[20,"松本市","安曇"],"3901516":[20,"松本市","安曇"],"3901520":[20,"松本市","安曇"],"3901611":[20,"松本市","奈川"],"3901701":[20,"松本市","梓川倭"],"3901702":[20,"松本市","梓川梓"],"3901703":[20,"松本市","梓川上野"],"3910000":[20,"茅野市",""],"3910001":[20,"茅野市","ちの"],"3910002":[20,"茅野市","塚原"],"3910003":[20,"茅野市","本町"],"3910004":[20,"茅野市","城山"],"3910005":[20,"茅野市","仲町"],"3910011":[20,"茅野市","玉川"],"3910012":[20,"茅野市","金沢"],"3910013":[20,"茅野市","宮川"],"3910021":[20,"諏訪郡富士見町","富士見"],"3910100":[20,"諏訪郡原村",""],"3910101":[20,"諏訪郡原村","大久保"],"3910102":[20,"諏訪郡原村","柳沢"],"3910103":[20,"諏訪郡原村","八ツ手"],"3910104":[20,"諏訪郡原村","払沢"],"3910105":[20,"諏訪郡原村","柏木"],"3910106":[20,"諏訪郡原村","菖蒲沢"],"3910107":[20,"諏訪郡原村","室内"],"3910108":[20,"諏訪郡原村","中新田"],"3910109":[20,"諏訪郡原村","南原"],"3910111":[20,"諏訪郡原村","上里"],"3910112":[20,"諏訪郡原村","農場"],"3910113":[20,"諏訪郡原村","やつがね"],"3910114":[20,"諏訪郡原村","ペンション"],"3910115":[20,"諏訪郡原村","原山"],"3910116":[20,"諏訪郡原村","判の木"],"3910211":[20,"茅野市","湖東"],"3910212":[20,"茅野市","北山"],"3910213":[20,"茅野市","豊平"],"3910214":[20,"茅野市","泉野"],"3910215":[20,"茅野市","中大塩"],"3910216":[20,"茅野市","米沢"],"3910301":[20,"茅野市","北山"],"3910321":[20,"北佐久郡立科町","芦田八ケ野"],"3920000":[20,"諏訪市",""],"3920001":[20,"諏訪市","大和"],"3920002":[20,"諏訪市","湯の脇"],"3920003":[20,"諏訪市","上諏訪"],"3920004":[20,"諏訪市","諏訪"],"3920005":[20,"諏訪市","岡村"],"3920006":[20,"諏訪市","元町"],"3920007":[20,"諏訪市","清水"],"3920008":[20,"諏訪市","霧ケ峰"],"3920009":[20,"諏訪市","杉菜池"],"3920010":[20,"諏訪市","渋崎"],"3920011":[20,"諏訪市","赤羽根"],"3920012":[20,"諏訪市","四賀"],"3920013":[20,"諏訪市","沖田町"],"3920014":[20,"諏訪市","南町"],"3920015":[20,"諏訪市","中洲"],"3920016":[20,"諏訪市","豊田"],"3920017":[20,"諏訪市","城南"],"3920021":[20,"諏訪市","上川"],"3920022":[20,"諏訪市","高島"],"3920023":[20,"諏訪市","小和田南"],"3920024":[20,"諏訪市","小和田"],"3920025":[20,"諏訪市","末広"],"3920026":[20,"諏訪市","大手"],"3920027":[20,"諏訪市","湖岸通り"],"3920131":[20,"諏訪市","湖南"],"3930000":[20,"諏訪郡下諏訪町",""],"3930001":[20,"諏訪郡下諏訪町","樋橋"],"3930002":[20,"諏訪郡下諏訪町","東俣"],"3930003":[20,"諏訪郡下諏訪町","萩倉"],"3930004":[20,"諏訪郡下諏訪町","東町下"],"3930005":[20,"諏訪郡下諏訪町","東町中"],"3930006":[20,"諏訪郡下諏訪町","東町上"],"3930007":[20,"諏訪郡下諏訪町","下屋敷"],"3930008":[20,"諏訪郡下諏訪町","町屋敷"],"3930011":[20,"諏訪郡下諏訪町","新町上"],"3930012":[20,"諏訪郡下諏訪町","横町"],"3930013":[20,"諏訪郡下諏訪町","小湯の上"],"3930014":[20,"諏訪郡下諏訪町","木の下"],"3930015":[20,"諏訪郡下諏訪町","立町"],"3930016":[20,"諏訪郡下諏訪町","湯田町"],"3930017":[20,"諏訪郡下諏訪町","湯田仲町"],"3930018":[20,"諏訪郡下諏訪町","新町下"],"3930019":[20,"諏訪郡下諏訪町","横町木の下"],"3930021":[20,"諏訪郡下諏訪町","武居"],"3930022":[20,"諏訪郡下諏訪町","関屋"],"3930023":[20,"諏訪郡下諏訪町","富ケ丘"],"3930024":[20,"諏訪郡下諏訪町","五官"],"3930025":[20,"諏訪郡下諏訪町","本郷"],"3930026":[20,"諏訪郡下諏訪町","久保海道"],"3930031":[20,"諏訪郡下諏訪町","東豊"],"3930032":[20,"諏訪郡下諏訪町","西浜"],"3930033":[20,"諏訪郡下諏訪町","高木"],"3930034":[20,"諏訪郡下諏訪町","高浜"],"3930035":[20,"諏訪郡下諏訪町","西豊"],"3930041":[20,"諏訪郡下諏訪町","西四王"],"3930042":[20,"諏訪郡下諏訪町","北四王"],"3930043":[20,"諏訪郡下諏訪町","東四王"],"3930044":[20,"諏訪郡下諏訪町","湖畔町"],"3930045":[20,"諏訪郡下諏訪町","南四王"],"3930046":[20,"諏訪郡下諏訪町","東赤砂"],"3930047":[20,"諏訪郡下諏訪町","西赤砂"],"3930051":[20,"諏訪郡下諏訪町","大社通"],"3930052":[20,"諏訪郡下諏訪町","上久保"],"3930053":[20,"諏訪郡下諏訪町","上馬場"],"3930054":[20,"諏訪郡下諏訪町","菅野町"],"3930055":[20,"諏訪郡下諏訪町","富士見町"],"3930056":[20,"諏訪郡下諏訪町","広瀬町"],"3930057":[20,"諏訪郡下諏訪町","友之町"],"3930061":[20,"諏訪郡下諏訪町","御田町"],"3930062":[20,"諏訪郡下諏訪町","平沢町"],"3930063":[20,"諏訪郡下諏訪町","花咲町"],"3930064":[20,"諏訪郡下諏訪町","中汐町"],"3930065":[20,"諏訪郡下諏訪町","魁町"],"3930066":[20,"諏訪郡下諏訪町","曙町"],"3930067":[20,"諏訪郡下諏訪町","矢木東"],"3930068":[20,"諏訪郡下諏訪町","春日町"],"3930071":[20,"諏訪郡下諏訪町","仲町"],"3930072":[20,"諏訪郡下諏訪町","桜町"],"3930073":[20,"諏訪郡下諏訪町","塚田町"],"3930074":[20,"諏訪郡下諏訪町","緑町"],"3930075":[20,"諏訪郡下諏訪町","中央通"],"3930076":[20,"諏訪郡下諏訪町","矢木西"],"3930077":[20,"諏訪郡下諏訪町","矢木町"],"3930078":[20,"諏訪郡下諏訪町","田中町"],"3930081":[20,"諏訪郡下諏訪町","社東町"],"3930082":[20,"諏訪郡下諏訪町","西弥生町"],"3930083":[20,"諏訪郡下諏訪町","東弥生町"],"3930084":[20,"諏訪郡下諏訪町","栄町"],"3930085":[20,"諏訪郡下諏訪町","東鷹野町"],"3930086":[20,"諏訪郡下諏訪町","清水町"],"3930087":[20,"諏訪郡下諏訪町","西鷹野町"],"3930091":[20,"諏訪郡下諏訪町","星が丘"],"3930092":[20,"諏訪郡下諏訪町","大門"],"3930093":[20,"諏訪郡下諏訪町","東山田"],"3940000":[20,"岡谷市",""],"3940001":[20,"岡谷市","今井"],"3940002":[20,"岡谷市","赤羽"],"3940003":[20,"岡谷市","加茂町"],"3940004":[20,"岡谷市","神明町"],"3940005":[20,"岡谷市","山下町"],"3940011":[20,"岡谷市","長地"],"3940021":[20,"岡谷市","郷田"],"3940022":[20,"岡谷市","銀座"],"3940023":[20,"岡谷市","東銀座"],"3940024":[20,"岡谷市","堀ノ内"],"3940025":[20,"岡谷市","大栄町"],"3940026":[20,"岡谷市","塚間町"],"3940027":[20,"岡谷市","中央町"],"3940028":[20,"岡谷市","本町"],"3940029":[20,"岡谷市","幸町"],"3940031":[20,"岡谷市","田中町"],"3940032":[20,"岡谷市","若宮"],"3940033":[20,"岡谷市","南宮"],"3940034":[20,"岡谷市","湖畔"],"3940035":[20,"岡谷市","天竜町"],"3940041":[20,"岡谷市","山手町"],"3940042":[20,"岡谷市","成田町"],"3940043":[20,"岡谷市","御倉町"],"3940044":[20,"岡谷市","湊"],"3940045":[20,"岡谷市","川岸東"],"3940046":[20,"岡谷市","川岸西"],"3940047":[20,"岡谷市","川岸中"],"3940048":[20,"岡谷市","川岸上"],"3940051":[20,"岡谷市","塩嶺"],"3940052":[20,"岡谷市","西林"],"3940053":[20,"岡谷市","芦ノ沢"],"3940054":[20,"岡谷市","半ノ木"],"3940055":[20,"岡谷市","内山"],"3940056":[20,"岡谷市","樋沢"],"3940081":[20,"岡谷市","長地権現町"],"3940082":[20,"岡谷市","長地御所"],"3940083":[20,"岡谷市","長地柴宮"],"3940084":[20,"岡谷市","長地片間町"],"3940085":[20,"岡谷市","長地小萩"],"3940086":[20,"岡谷市","長地源"],"3940087":[20,"岡谷市","長地鎮"],"3940088":[20,"岡谷市","長地梨久保"],"3940089":[20,"岡谷市","長地出早"],"3940091":[20,"岡谷市",""],"3950000":[20,"飯田市",""],"3950001":[20,"飯田市","座光寺"],"3950002":[20,"飯田市","上郷飯沼"],"3950003":[20,"飯田市","上郷別府"],"3950004":[20,"飯田市","上郷黒田"],"3950011":[20,"飯田市","大門町"],"3950012":[20,"飯田市","大王路"],"3950013":[20,"飯田市","小伝馬町"],"3950014":[20,"飯田市","桜町"],"3950015":[20,"飯田市","江戸町"],"3950016":[20,"飯田市","伝馬町"],"3950017":[20,"飯田市","東新町"],"3950018":[20,"飯田市","諏訪町"],"3950021":[20,"飯田市","仲ノ町"],"3950022":[20,"飯田市","浜井町"],"3950023":[20,"飯田市","江戸浜町"],"3950024":[20,"飯田市","東栄町"],"3950025":[20,"飯田市","東中央通り"],"3950026":[20,"飯田市","鼎西鼎"],"3950027":[20,"飯田市","馬場町"],"3950028":[20,"飯田市","長姫町"],"3950029":[20,"飯田市","二本松"],"3950031":[20,"飯田市","銀座"],"3950032":[20,"飯田市","主税町"],"3950033":[20,"飯田市","常盤町"],"3950034":[20,"飯田市","追手町"],"3950035":[20,"飯田市","水の手町"],"3950036":[20,"飯田市","愛宕町"],"3950037":[20,"飯田市","南常盤町"],"3950041":[20,"飯田市","中央通り"],"3950042":[20,"飯田市","松尾町"],"3950043":[20,"飯田市","通り町"],"3950044":[20,"飯田市","本町"],"3950045":[20,"飯田市","知久町"],"3950046":[20,"飯田市","扇町"],"3950048":[20,"飯田市","滝の沢"],"3950051":[20,"飯田市","高羽町"],"3950052":[20,"飯田市","元町"],"3950053":[20,"飯田市","大久保町"],"3950054":[20,"飯田市","箕瀬町"],"3950055":[20,"飯田市","旭町"],"3950056":[20,"飯田市","大通"],"3950061":[20,"飯田市","正永町"],"3950062":[20,"飯田市","砂払町"],"3950063":[20,"飯田市","羽場町"],"3950064":[20,"飯田市","羽場仲畑"],"3950065":[20,"飯田市","羽場上河原"],"3950066":[20,"飯田市","羽場赤坂"],"3950067":[20,"飯田市","羽場権現"],"3950068":[20,"飯田市","大休"],"3950071":[20,"飯田市","今宮町"],"3950072":[20,"飯田市","曙町"],"3950073":[20,"飯田市","羽場坂町"],"3950074":[20,"飯田市","松川町"],"3950075":[20,"飯田市","白山通り"],"3950076":[20,"飯田市","白山町"],"3950077":[20,"飯田市","丸山町"],"3950081":[20,"飯田市","宮ノ上"],"3950082":[20,"飯田市","宮の前"],"3950083":[20,"飯田市","錦町"],"3950084":[20,"飯田市","鈴加町"],"3950085":[20,"飯田市","吾妻町"],"3950086":[20,"飯田市","東和町"],"3950151":[20,"飯田市","北方"],"3950152":[20,"飯田市","育良町"],"3950153":[20,"飯田市","上殿岡"],"3950154":[20,"飯田市","下殿岡"],"3950155":[20,"飯田市","三日市場"],"3950156":[20,"飯田市","中村"],"3950157":[20,"飯田市","大瀬木"],"3950241":[20,"飯田市","久米"],"3950242":[20,"飯田市","竹佐"],"3950243":[20,"飯田市","箱川"],"3950244":[20,"飯田市","山本"],"3950245":[20,"飯田市","山本二ツ山団地"],"3950300":[20,"下伊那郡阿智村",""],"3950301":[20,"下伊那郡阿智村","春日"],"3950302":[20,"下伊那郡阿智村","伍和"],"3950303":[20,"下伊那郡阿智村","駒場"],"3950304":[20,"下伊那郡阿智村","智里"],"3950305":[20,"下伊那郡阿智村","駒"],"3950401":[20,"下伊那郡阿智村","清内路"],"3950501":[20,"下伊那郡阿智村","浪合"],"3950601":[20,"下伊那郡平谷村","平谷村一円"],"3950701":[20,"下伊那郡根羽村","根羽村一円"],"3950801":[20,"飯田市","鼎中平"],"3950802":[20,"飯田市","鼎下茶屋"],"3950803":[20,"飯田市","鼎下山"],"3950804":[20,"飯田市","鼎名古熊"],"3950805":[20,"飯田市","鼎一色"],"3950806":[20,"飯田市","鼎上山"],"3950807":[20,"飯田市","鼎切石"],"3950808":[20,"飯田市","鼎上茶屋"],"3950811":[20,"飯田市","松尾上溝"],"3950812":[20,"飯田市","松尾代田"],"3950813":[20,"飯田市","毛賀"],"3950814":[20,"飯田市","八幡町"],"3950815":[20,"飯田市","松尾常盤台"],"3950816":[20,"飯田市","松尾久井"],"3950817":[20,"飯田市","鼎東鼎"],"3950821":[20,"飯田市","松尾新井"],"3950822":[20,"飯田市","松尾寺所"],"3950823":[20,"飯田市","松尾明"],"3950824":[20,"飯田市","松尾清水"],"3950825":[20,"飯田市","松尾城"],"3950826":[20,"飯田市","松尾水城"],"3951100":[20,"下伊那郡喬木村",""],"3951101":[20,"下伊那郡喬木村","阿島"],"3951102":[20,"下伊那郡喬木村","加々須"],"3951103":[20,"下伊那郡喬木村","大島"],"3951104":[20,"下伊那郡喬木村","氏乗"],"3951105":[20,"下伊那郡喬木村","大和知"],"3951106":[20,"下伊那郡喬木村","富田"],"3951107":[20,"下伊那郡喬木村","小川"],"3951108":[20,"下伊那郡喬木村","伊久間"],"3960000":[20,"伊那市",""],"3960001":[20,"伊那市","福島"],"3960002":[20,"伊那市","手良沢岡"],"3960003":[20,"伊那市","手良野口"],"3960004":[20,"伊那市","手良中坪"],"3960005":[20,"伊那市","野底"],"3960006":[20,"伊那市","上牧"],"3960007":[20,"伊那市","若宮"],"3960008":[20,"伊那市","上の原"],"3960009":[20,"伊那市","日影"],"3960010":[20,"伊那市","境"],"3960011":[20,"伊那市","伊那部"],"3960012":[20,"伊那市","上新田"],"3960013":[20,"伊那市","下新田"],"3960014":[20,"伊那市","狐島"],"3960015":[20,"伊那市","中央"],"3960021":[20,"伊那市","伊那"],"3960022":[20,"伊那市","御園"],"3960023":[20,"伊那市","山寺"],"3960024":[20,"伊那市","坂下"],"3960025":[20,"伊那市","荒井"],"3960026":[20,"伊那市","西町"],"3960027":[20,"伊那市","ますみヶ丘"],"3960028":[20,"伊那市","荒井内の萱"],"3960029":[20,"伊那市","横山"],"3960030":[20,"伊那市","平沢"],"3960031":[20,"伊那市","中の原"],"3960032":[20,"伊那市","小沢"],"3960033":[20,"伊那市","小四郎久保"],"3960041":[20,"伊那市","西箕輪"],"3960111":[20,"伊那市","美篶"],"3960112":[20,"伊那市","前原"],"3960113":[20,"伊那市","美原"],"3960114":[20,"伊那市","仙美"],"3960211":[20,"伊那市","高遠町西高遠"],"3960212":[20,"伊那市","高遠町長藤"],"3960213":[20,"伊那市","高遠町東高遠"],"3960214":[20,"伊那市","高遠町勝間"],"3960215":[20,"伊那市","高遠町小原"],"3960216":[20,"伊那市","高遠町下山田"],"3960217":[20,"伊那市","高遠町上山田"],"3960301":[20,"伊那市","高遠町藤沢"],"3960302":[20,"伊那市","高遠町芝平"],"3960303":[20,"伊那市","高遠町荊口"],"3960304":[20,"伊那市","高遠町山室"],"3960305":[20,"伊那市","高遠町長藤"],"3960401":[20,"伊那市","長谷非持"],"3960402":[20,"伊那市","長谷溝口"],"3960403":[20,"伊那市","長谷黒河内"],"3960404":[20,"伊那市","長谷中尾"],"3960405":[20,"伊那市","長谷市野瀬"],"3960406":[20,"伊那市","長谷杉島"],"3960407":[20,"伊那市","長谷浦"],"3960621":[20,"伊那市","富県"],"3970000":[20,"木曽郡木曽町",""],"3970001":[20,"木曽郡木曽町","福島"],"3970002":[20,"木曽郡木曽町","新開"],"3970003":[20,"木曽郡木曽町","新開福"],"3970101":[20,"木曽郡木曽町","三岳"],"3970201":[20,"木曽郡王滝村","王滝村一円"],"3970301":[20,"木曽郡木曽町","開田高原末川"],"3970302":[20,"木曽郡木曽町","開田高原西野"],"3980000":[20,"大町市",""],"3980001":[20,"大町市","平"],"3980002":[20,"大町市","大町"],"3980003":[20,"大町市","社"],"3980004":[20,"大町市","常盤"],"3990000":[20,"松本市",""],"3990001":[20,"松本市","宮田"],"3990002":[20,"松本市","芳野"],"3990004":[20,"松本市","市場"],"3990005":[20,"松本市","野溝木工"],"3990006":[20,"松本市","野溝西"],"3990007":[20,"松本市","石芝"],"3990011":[20,"松本市","寿北"],"3990012":[20,"松本市","寿白瀬渕"],"3990014":[20,"松本市","平田東"],"3990015":[20,"松本市","平田西"],"3990021":[20,"松本市","寿豊丘"],"3990022":[20,"松本市","松原"],"3990023":[20,"松本市","内田"],"3990024":[20,"松本市","寿小赤"],"3990025":[20,"松本市","寿台"],"3990026":[20,"松本市","寿中"],"3990027":[20,"松本市","寿南"],"3990033":[20,"松本市","笹賀"],"3990034":[20,"松本市","野溝東"],"3990035":[20,"松本市","村井町北"],"3990036":[20,"松本市","村井町南"],"3990037":[20,"松本市","村井町西"],"3990038":[20,"松本市","小屋南"],"3990039":[20,"松本市","小屋北"],"3990071":[20,"塩尻市","片丘"],"3990101":[20,"諏訪郡富士見町","境"],"3990102":[20,"諏訪郡富士見町","落合"],"3990200":[20,"諏訪郡富士見町",""],"3990211":[20,"諏訪郡富士見町","富士見"],"3990212":[20,"諏訪郡富士見町","立沢"],"3990213":[20,"諏訪郡富士見町","乙事"],"3990214":[20,"諏訪郡富士見町","落合"],"3990400":[20,"上伊那郡辰野町",""],"3990421":[20,"上伊那郡辰野町","辰野"],"3990422":[20,"上伊那郡辰野町","平出"],"3990423":[20,"上伊那郡辰野町","沢底"],"3990424":[20,"上伊那郡辰野町","赤羽"],"3990425":[20,"上伊那郡辰野町","樋口"],"3990426":[20,"上伊那郡辰野町","宮木"],"3990427":[20,"上伊那郡辰野町","中央"],"3990428":[20,"上伊那郡辰野町","伊那富"],"3990511":[20,"上伊那郡辰野町","横川"],"3990512":[20,"上伊那郡辰野町","上島"],"3990601":[20,"上伊那郡辰野町","小野"],"3990651":[20,"塩尻市","北小野"],"3990700":[20,"塩尻市",""],"3990701":[20,"塩尻市","広丘吉田"],"3990702":[20,"塩尻市","広丘野村"],"3990703":[20,"塩尻市","広丘高出"],"3990704":[20,"塩尻市","広丘郷原"],"3990705":[20,"塩尻市","広丘堅石"],"3990706":[20,"塩尻市","広丘原新田"],"3990711":[20,"塩尻市","片丘"],"3990712":[20,"塩尻市","塩尻町"],"3990713":[20,"塩尻市","大小屋"],"3990714":[20,"塩尻市","堀ノ内"],"3990715":[20,"塩尻市","長畝"],"3990716":[20,"塩尻市","桟敷"],"3990721":[20,"塩尻市","金井"],"3990722":[20,"塩尻市","柿沢"],"3990723":[20,"塩尻市","旧塩尻"],"3990724":[20,"塩尻市","上西条"],"3990725":[20,"塩尻市","中西条"],"3990726":[20,"塩尻市","下西条"],"3990727":[20,"塩尻市","みどり湖"],"3990728":[20,"塩尻市","峰原"],"3990731":[20,"塩尻市","大門六番町"],"3990732":[20,"塩尻市","大門五番町"],"3990733":[20,"塩尻市","大門三番町"],"3990734":[20,"塩尻市","大門四番町"],"3990735":[20,"塩尻市","大門二番町"],"3990736":[20,"塩尻市","大門一番町"],"3990737":[20,"塩尻市","大門八番町"],"3990738":[20,"塩尻市","大門七番町"],"3990741":[20,"塩尻市","大門幸町"],"3990742":[20,"塩尻市","大門泉町"],"3990743":[20,"塩尻市","大門田川町"],"3990744":[20,"塩尻市","大門七区"],"3990745":[20,"塩尻市","大門桔梗町"],"3990746":[20,"塩尻市","大門並木町"],"3991200":[20,"下伊那郡天龍村",""],"3991201":[20,"下伊那郡天龍村","平岡"],"3991202":[20,"下伊那郡天龍村","神原"],"3991203":[20,"下伊那郡天龍村","長島"],"3991221":[20,"飯田市","南信濃南和田"],"3991311":[20,"飯田市","南信濃和田"],"3991312":[20,"飯田市","南信濃八重河内"],"3991313":[20,"飯田市","南信濃南和田"],"3991401":[20,"飯田市","南信濃木沢"],"3991403":[20,"飯田市","上村"],"3991500":[20,"下伊那郡阿南町",""],"3991501":[20,"下伊那郡阿南町","北條"],"3991502":[20,"下伊那郡阿南町","東條"],"3991503":[20,"下伊那郡阿南町","南條"],"3991504":[20,"下伊那郡阿南町","西條"],"3991505":[20,"下伊那郡阿南町","富草"],"3991601":[20,"下伊那郡売木村","売木村一円"],"3991611":[20,"下伊那郡阿南町","和合"],"3991612":[20,"下伊那郡阿南町","新野"],"3991801":[20,"下伊那郡泰阜村","泰阜村一円"],"3992100":[20,"下伊那郡下條村",""],"3992101":[20,"下伊那郡下條村","睦沢"],"3992102":[20,"下伊那郡下條村","陽皐"],"3992221":[20,"飯田市","龍江"],"3992222":[20,"飯田市","千代"],"3992223":[20,"飯田市","千栄"],"3992431":[20,"飯田市","川路"],"3992432":[20,"飯田市","下瀬"],"3992433":[20,"飯田市","立石"],"3992434":[20,"飯田市","伊豆木"],"3992561":[20,"飯田市","駄科"],"3992562":[20,"飯田市","長野原"],"3992563":[20,"飯田市","時又"],"3992564":[20,"飯田市","上川路"],"3992565":[20,"飯田市","桐林"],"3992566":[20,"飯田市","嶋"],"3992601":[20,"飯田市","虎岩"],"3992602":[20,"飯田市","下久堅下虎岩"],"3992603":[20,"飯田市","下久堅知久平"],"3992604":[20,"飯田市","下久堅柿野沢"],"3992605":[20,"飯田市","下久堅小林"],"3992606":[20,"飯田市","下久堅稲葉"],"3992607":[20,"飯田市","下久堅南原"],"3992611":[20,"飯田市","上久堅"],"3992612":[20,"飯田市","上久堅戊"],"3993100":[20,"下伊那郡高森町",""],"3993101":[20,"下伊那郡高森町","山吹"],"3993102":[20,"下伊那郡高森町","吉田"],"3993103":[20,"下伊那郡高森町","下市田"],"3993104":[20,"下伊那郡高森町","上市田"],"3993105":[20,"下伊那郡高森町","牛牧"],"3993106":[20,"下伊那郡高森町","大島山"],"3993107":[20,"下伊那郡高森町","出原"],"3993200":[20,"下伊那郡豊丘村",""],"3993201":[20,"下伊那郡豊丘村","河野"],"3993202":[20,"下伊那郡豊丘村","神稲"],"3993300":[20,"下伊那郡松川町",""],"3993301":[20,"下伊那郡松川町","上片桐"],"3993302":[20,"下伊那郡松川町","生田"],"3993303":[20,"下伊那郡松川町","元大島"],"3993304":[20,"下伊那郡松川町","大島"],"3993311":[20,"下伊那郡豊丘村","河野"],"3993500":[20,"下伊那郡大鹿村",""],"3993501":[20,"下伊那郡大鹿村","鹿塩"],"3993502":[20,"下伊那郡大鹿村","大河原"],"3993700":[20,"上伊那郡飯島町",""],"3993701":[20,"上伊那郡飯島町","田切"],"3993702":[20,"上伊那郡飯島町","飯島"],"3993703":[20,"上伊那郡飯島町","日曽利"],"3993704":[20,"上伊那郡飯島町","本郷"],"3993705":[20,"上伊那郡飯島町","七久保"],"3993800":[20,"上伊那郡中川村",""],"3993801":[20,"上伊那郡中川村","大草"],"3993802":[20,"上伊那郡中川村","片桐"],"3993803":[20,"上伊那郡中川村","葛島"],"3993804":[20,"上伊那郡中川村","四徳"],"3994100":[20,"駒ヶ根市",""],"3994101":[20,"駒ヶ根市","下平"],"3994102":[20,"駒ヶ根市","飯坂"],"3994103":[20,"駒ヶ根市","梨の木"],"3994104":[20,"駒ヶ根市","経塚"],"3994105":[20,"駒ヶ根市","赤須東"],"3994106":[20,"駒ヶ根市","東町"],"3994107":[20,"駒ヶ根市","南田"],"3994108":[20,"駒ヶ根市","下市場"],"3994111":[20,"駒ヶ根市","北町"],"3994112":[20,"駒ヶ根市","中央"],"3994113":[20,"駒ヶ根市","赤須町"],"3994114":[20,"駒ヶ根市","上穂南"],"3994115":[20,"駒ヶ根市","上穂栄町"],"3994116":[20,"駒ヶ根市","上穂北"],"3994117":[20,"駒ヶ根市","赤穂"],"3994231":[20,"駒ヶ根市","中沢"],"3994232":[20,"駒ヶ根市","下平"],"3994301":[20,"上伊那郡宮田村","宮田村一円"],"3994321":[20,"駒ヶ根市","東伊那"],"3994431":[20,"伊那市","西春近"],"3994432":[20,"伊那市","東春近"],"3994511":[20,"上伊那郡南箕輪村","南箕輪村一円"],"3994600":[20,"上伊那郡箕輪町",""],"3994601":[20,"上伊那郡箕輪町","中箕輪"],"3994602":[20,"上伊那郡箕輪町","東箕輪"],"3994603":[20,"上伊那郡箕輪町","三日町"],"3994604":[20,"上伊那郡箕輪町","福与"],"3994605":[20,"上伊那郡箕輪町","中曽根"],"3995300":[20,"木曽郡南木曽町",""],"3995301":[20,"木曽郡南木曽町","読書"],"3995302":[20,"木曽郡南木曽町","吾妻"],"3995303":[20,"木曽郡南木曽町","田立"],"3995500":[20,"木曽郡大桑村",""],"3995501":[20,"木曽郡大桑村","殿"],"3995502":[20,"木曽郡大桑村","須原"],"3995503":[20,"木曽郡大桑村","長野"],"3995504":[20,"木曽郡大桑村","野尻"],"3995600":[20,"木曽郡上松町",""],"3995601":[20,"木曽郡上松町","上松"],"3995602":[20,"木曽郡上松町","本町通り"],"3995603":[20,"木曽郡上松町","駅前通り"],"3995604":[20,"木曽郡上松町","正島町"],"3995605":[20,"木曽郡上松町","栄町"],"3995606":[20,"木曽郡上松町","緑町"],"3995607":[20,"木曽郡上松町","小川"],"3995608":[20,"木曽郡上松町","荻原"],"3995609":[20,"木曽郡上松町","旭町"],"3996101":[20,"木曽郡木曽町","日義"],"3996200":[20,"木曽郡木祖村",""],"3996201":[20,"木曽郡木祖村","薮原"],"3996202":[20,"木曽郡木祖村","菅"],"3996203":[20,"木曽郡木祖村","小木曽"],"3996301":[20,"塩尻市","贄川"],"3996302":[20,"塩尻市","木曽平沢"],"3996303":[20,"塩尻市","奈良井"],"3996461":[20,"塩尻市","宗賀"],"3996462":[20,"塩尻市","洗馬"],"3997101":[20,"安曇野市","明科東川手"],"3997102":[20,"安曇野市","明科中川手"],"3997103":[20,"安曇野市","明科光"],"3997104":[20,"安曇野市","明科七貴"],"3997105":[20,"安曇野市","明科南陸郷"],"3997200":[20,"東筑摩郡生坂村",""],"3997201":[20,"東筑摩郡生坂村",""],"3997202":[20,"東筑摩郡生坂村","北陸郷"],"3997301":[20,"大町市","八坂"],"3997302":[20,"大町市","八坂菖蒲"],"3997311":[20,"東筑摩郡生坂村","東広津"],"3997401":[20,"松本市","五常"],"3997402":[20,"松本市","会田"],"3997403":[20,"松本市","穴沢"],"3997404":[20,"松本市","取出"],"3997405":[20,"松本市","板場"],"3997411":[20,"松本市","中川"],"3997412":[20,"松本市","保福寺町"],"3997413":[20,"松本市","金山町"],"3997414":[20,"松本市","殿野入"],"3997415":[20,"松本市","赤怒田"],"3997416":[20,"松本市","七嵐"],"3997417":[20,"松本市","刈谷原町"],"3997418":[20,"松本市","反町"],"3997500":[20,"東筑摩郡筑北村",""],"3997501":[20,"東筑摩郡筑北村","西条"],"3997502":[20,"東筑摩郡筑北村","東条"],"3997503":[20,"東筑摩郡筑北村","大沢新田"],"3997504":[20,"東筑摩郡筑北村","乱橋"],"3997601":[20,"東筑摩郡筑北村","坂北"],"3997700":[20,"東筑摩郡麻績村",""],"3997701":[20,"東筑摩郡麻績村","麻"],"3997702":[20,"東筑摩郡麻績村","日"],"3997711":[20,"東筑摩郡筑北村","坂井"],"3998101":[20,"安曇野市","三郷明盛"],"3998102":[20,"安曇野市","三郷温"],"3998103":[20,"安曇野市","三郷小倉"],"3998200":[20,"安曇野市",""],"3998201":[20,"安曇野市","豊科南穂高"],"3998202":[20,"安曇野市","豊科光"],"3998203":[20,"安曇野市","豊科田沢"],"3998204":[20,"安曇野市","豊科高家"],"3998205":[20,"安曇野市","豊科"],"3998211":[20,"安曇野市","堀金烏川"],"3998212":[20,"安曇野市","堀金三田"],"3998251":[20,"松本市","島内"],"3998301":[20,"安曇野市","穂高有明"],"3998302":[20,"安曇野市","穂高北穂高"],"3998303":[20,"安曇野市","穂高"],"3998304":[20,"安曇野市","穂高柏原"],"3998305":[20,"安曇野市","穂高牧"],"3998501":[20,"北安曇郡松川村","松川村一円"],"3998600":[20,"北安曇郡池田町",""],"3998601":[20,"北安曇郡池田町","池田"],"3998602":[20,"北安曇郡池田町","会染"],"3998603":[20,"北安曇郡池田町","中鵜"],"3998604":[20,"北安曇郡池田町","広津"],"3998605":[20,"北安曇郡池田町","陸郷"],"3999101":[20,"大町市","美麻"],"3999211":[20,"北安曇郡白馬村","神城"],"3999300":[20,"北安曇郡白馬村",""],"3999301":[20,"北安曇郡白馬村","北城"],"3999400":[20,"北安曇郡小谷村",""],"3999421":[20,"北安曇郡小谷村","中小谷"],"3999422":[20,"北安曇郡小谷村","千国"],"3999511":[20,"北安曇郡小谷村","中土"],"3999601":[20,"北安曇郡小谷村","北小谷"]}