{"4100001":[22,"沼津市","足高"],"4100002":[22,"沼津市","東沢田"],"4100003":[22,"沼津市","新沢田町"],"4100004":[22,"沼津市","本田町"],"4100005":[22,"沼津市","双葉町"],"4100006":[22,"沼津市","中沢田"],"4100007":[22,"沼津市","西沢田"],"4100011":[22,"沼津市","岡宮"],"4100012":[22,"沼津市","岡一色"],"4100013":[22,"沼津市","東熊堂"],"4100014":[22,"沼津市","松沢町"],"4100015":[22,"沼津市","駿河台"],"4100016":[22,"沼津市","高砂町"],"4100017":[22,"沼津市","高尾台"],"4100018":[22,"沼津市","豊町"],"4100021":[22,"沼津市","小林台"],"4100022":[22,"沼津市","大岡"],"4100031":[22,"沼津市","三枚橋"],"4100032":[22,"沼津市","日の出町"],"4100033":[22,"沼津市","杉崎町"],"4100034":[22,"沼津市","富士見町"],"4100035":[22,"沼津市","山王台"],"4100036":[22,"沼津市","平町"],"4100037":[22,"沼津市","三枚橋町"],"4100038":[22,"沼津市","三芳町"],"4100041":[22,"沼津市","筒井町"],"4100042":[22,"沼津市","神田町"],"4100043":[22,"沼津市","柳町"],"4100044":[22,"沼津市","五月町"],"4100045":[22,"沼津市","泉町"],"4100046":[22,"沼津市","米山町"],"4100047":[22,"沼津市","庄栄町"],"4100048":[22,"沼津市","新宿町"],"4100049":[22,"沼津市","江原町"],"4100051":[22,"沼津市","西熊堂"],"4100052":[22,"沼津市","沢田町"],"4100053":[22,"沼津市","寿町"],"4100054":[22,"沼津市","北高島町"],"4100055":[22,"沼津市","高島本町"],"4100056":[22,"沼津市","高島町"],"4100057":[22,"沼津市","高沢町"],"4100058":[22,"沼津市","沼北町"],"4100059":[22,"沼津市","若葉町"],"4100061":[22,"沼津市","北園町"],"4100062":[22,"沼津市","宮前町"],"4100063":[22,"沼津市","緑ケ丘"],"4100064":[22,"沼津市","共栄町"],"4100065":[22,"沼津市","花園町"],"4100101":[22,"沼津市","多比"],"4100102":[22,"沼津市","口野"],"4100103":[22,"沼津市","江浦"],"4100104":[22,"沼津市","獅子浜"],"4100105":[22,"沼津市","馬込"],"4100106":[22,"沼津市","志下"],"4100221":[22,"沼津市","内浦重寺"],"4100222":[22,"沼津市","内浦小海"],"4100223":[22,"沼津市","内浦三津"],"4100224":[22,"沼津市","内浦長浜"],"4100225":[22,"沼津市","内浦重須"],"4100231":[22,"沼津市","西浦木負"],"4100232":[22,"沼津市","西浦河内"],"4100233":[22,"沼津市","西浦久連"],"4100234":[22,"沼津市","西浦平沢"],"4100235":[22,"沼津市","西浦立保"],"4100241":[22,"沼津市","西浦古宇"],"4100242":[22,"沼津市","西浦足保"],"4100243":[22,"沼津市","西浦久料"],"4100244":[22,"沼津市","西浦江梨"],"4100301":[22,"沼津市","宮本"],"4100302":[22,"沼津市","東椎路"],"4100303":[22,"沼津市","西椎路"],"4100304":[22,"沼津市","東原"],"4100305":[22,"沼津市","鳥谷"],"4100306":[22,"沼津市","大塚"],"4100307":[22,"沼津市","青野"],"4100308":[22,"沼津市","柳沢"],"4100309":[22,"沼津市","根古屋"],"4100311":[22,"沼津市","原町中"],"4100312":[22,"沼津市","原"],"4100313":[22,"沼津市","西添町"],"4100314":[22,"沼津市","一本松"],"4100315":[22,"沼津市","桃里"],"4100316":[22,"沼津市","植田"],"4100317":[22,"沼津市","石川"],"4100318":[22,"沼津市","平沼"],"4100319":[22,"沼津市","井出"],"4100321":[22,"沼津市","西野"],"4100801":[22,"沼津市","大手町"],"4100802":[22,"沼津市","上土町"],"4100803":[22,"沼津市","添地町"],"4100804":[22,"沼津市","西条町"],"4100805":[22,"沼津市","白銀町"],"4100806":[22,"沼津市","丸子町"],"4100807":[22,"沼津市","錦町"],"4100811":[22,"沼津市","中瀬町"],"4100812":[22,"沼津市","山ケ下町"],"4100813":[22,"沼津市","上香貫"],"4100814":[22,"沼津市","玉江町"],"4100815":[22,"沼津市","南本郷町"],"4100816":[22,"沼津市","住吉町"],"4100817":[22,"沼津市","本郷町"],"4100818":[22,"沼津市","中原町"],"4100819":[22,"沼津市","黒瀬町"],"4100821":[22,"沼津市","大平"],"4100822":[22,"沼津市","下香貫"],"4100823":[22,"沼津市","我入道"],"4100824":[22,"沼津市","香貫が丘"],"4100831":[22,"沼津市","市場町"],"4100832":[22,"沼津市","御幸町"],"4100833":[22,"沼津市","三園町"],"4100834":[22,"沼津市","槇島町"],"4100835":[22,"沼津市","西島町"],"4100836":[22,"沼津市","吉田町"],"4100841":[22,"沼津市","下河原町"],"4100842":[22,"沼津市","蛇松町"],"4100843":[22,"沼津市","蓼原町"],"4100844":[22,"沼津市","春日町"],"4100845":[22,"沼津市","千本港町"],"4100846":[22,"沼津市","千本東町"],"4100847":[22,"沼津市","千本中町"],"4100848":[22,"沼津市","千本西町"],"4100849":[22,"沼津市","千本郷林"],"4100851":[22,"沼津市","宮町"],"4100852":[22,"沼津市","旭町"],"4100853":[22,"沼津市","常盤町"],"4100854":[22,"沼津市","千本常盤町"],"4100855":[22,"沼津市","千本緑町"],"4100861":[22,"沼津市","真砂町"],"4100862":[22,"沼津市","幸町"],"4100863":[22,"沼津市","下一丁田"],"4100864":[22,"沼津市","松下"],"4100865":[22,"沼津市","東間門"],"4100866":[22,"沼津市","市道"],"4100867":[22,"沼津市","下中溝"],"4100868":[22,"沼津市","下小路町"],"4100871":[22,"沼津市","西間門"],"4100872":[22,"沼津市","小諏訪"],"4100873":[22,"沼津市","大諏訪"],"4100874":[22,"沼津市","松長"],"4100875":[22,"沼津市","今沢"],"4100876":[22,"沼津市","北今沢"],"4100881":[22,"沼津市","八幡町"],"4100882":[22,"沼津市","町方町"],"4100883":[22,"沼津市","大門町"],"4100884":[22,"沼津市","本町"],"4100885":[22,"沼津市","下本町"],"4100886":[22,"沼津市","浅間町"],"4100887":[22,"沼津市","東宮後町"],"4100888":[22,"沼津市","末広町"],"4100891":[22,"沼津市","通横町"],"4100892":[22,"沼津市","魚町"],"4100893":[22,"沼津市","くまだか町"],"4100894":[22,"沼津市","仲町"],"4100895":[22,"沼津市","新町"],"4101100":[22,"裾野市",""],"4101101":[22,"裾野市","岩波"],"4101102":[22,"裾野市","深良"],"4101103":[22,"裾野市","葛山"],"4101104":[22,"裾野市","今里"],"4101105":[22,"裾野市","下和田"],"4101106":[22,"裾野市","金沢"],"4101107":[22,"裾野市","御宿"],"4101108":[22,"裾野市","上ケ田"],"4101109":[22,"裾野市","呼子"],"4101111":[22,"裾野市","久根"],"4101112":[22,"裾野市","公文名"],"4101113":[22,"裾野市","稲荷"],"4101114":[22,"裾野市","大畑"],"4101115":[22,"裾野市","千福が丘"],"4101116":[22,"裾野市","千福"],"4101117":[22,"裾野市","石脇"],"4101118":[22,"裾野市","佐野"],"4101121":[22,"裾野市","茶畑"],"4101122":[22,"裾野市","麦塚"],"4101123":[22,"裾野市","伊豆島田"],"4101124":[22,"裾野市","水窪"],"4101125":[22,"裾野市","富沢"],"4101126":[22,"裾野市","桃園"],"4101127":[22,"裾野市","平松"],"4101128":[22,"裾野市","二ツ屋"],"4101231":[22,"裾野市","須山"],"4101300":[22,"駿東郡小山町",""],"4101301":[22,"駿東郡小山町","柳島"],"4101302":[22,"駿東郡小山町","中島"],"4101303":[22,"駿東郡小山町","生土"],"4101304":[22,"駿東郡小山町","藤曲"],"4101305":[22,"駿東郡小山町","湯船"],"4101306":[22,"駿東郡小山町","上野"],"4101307":[22,"駿東郡小山町","中日向"],"4101308":[22,"駿東郡小山町","大御神"],"4101311":[22,"駿東郡小山町","小山"],"4101312":[22,"駿東郡小山町","菅沼"],"4101313":[22,"駿東郡小山町","竹之下"],"4101314":[22,"駿東郡小山町","新柴"],"4101315":[22,"駿東郡小山町","桑木"],"4101316":[22,"駿東郡小山町","下古城"],"4101317":[22,"駿東郡小山町","大胡田"],"4101321":[22,"駿東郡小山町","阿多野"],"4101322":[22,"駿東郡小山町","吉久保"],"4101323":[22,"駿東郡小山町","上古城"],"4101324":[22,"駿東郡小山町","下小林"],"4101325":[22,"駿東郡小山町","一色"],"4101326":[22,"駿東郡小山町","用沢"],"4101327":[22,"駿東郡小山町","棚頭"],"4101431":[22,"駿東郡小山町","須走"],"4101432":[22,"駿東郡小山町","自衛隊富士学校"],"4102101":[22,"伊豆の国市","小松ケ原"],"4102102":[22,"伊豆の国市","富士見ニュータウン"],"4102103":[22,"伊豆の国市","エメラルドタウン"],"4102111":[22,"伊豆の国市","立花台"],"4102112":[22,"伊豆の国市","内中"],"4102113":[22,"伊豆の国市","中"],"4102114":[22,"伊豆の国市","南條"],"4102121":[22,"伊豆の国市","中條"],"4102122":[22,"伊豆の国市","寺家"],"4102123":[22,"伊豆の国市","四日町"],"4102124":[22,"伊豆の国市","原木"],"4102131":[22,"伊豆の国市","長崎"],"4102132":[22,"伊豆の国市","奈古谷"],"4102133":[22,"伊豆の国市","韮山多田"],"4102141":[22,"伊豆の国市","韮山山木"],"4102142":[22,"伊豆の国市","韮山金谷"],"4102143":[22,"伊豆の国市","韮山韮山"],"4102144":[22,"伊豆の国市","韮山土手和田"],"4102200":[22,"伊豆の国市",""],"4102201":[22,"伊豆の国市","古奈"],"4102202":[22,"伊豆の国市","天野"],"4102203":[22,"伊豆の国市","小坂"],"4102204":[22,"伊豆の国市","墹之上"],"4102205":[22,"伊豆の国市","富士見"],"4102211":[22,"伊豆の国市","長岡"],"4102212":[22,"伊豆の国市","長瀬"],"4102213":[22,"伊豆の国市","戸沢"],"4102214":[22,"伊豆の国市","花坂"],"4102221":[22,"伊豆の国市","南江間"],"4102223":[22,"伊豆の国市","北江間"],"4102301":[22,"伊豆の国市","田中山"],"4102302":[22,"伊豆の国市","宗光寺"],"4102303":[22,"伊豆の国市","立花"],"4102304":[22,"伊豆の国市","宗光寺"],"4102311":[22,"伊豆の国市","浮橋"],"4102312":[22,"伊豆の国市","長者原"],"4102313":[22,"伊豆の国市","田原野"],"4102314":[22,"伊豆の国市","下畑"],"4102315":[22,"伊豆の国市","田京"],"4102316":[22,"伊豆の国市","御門"],"4102317":[22,"伊豆の国市","守木"],"4102318":[22,"伊豆の国市","白山堂"],"4102321":[22,"伊豆の国市","三福"],"4102322":[22,"伊豆の国市","吉田"],"4102323":[22,"伊豆の国市","大仁"],"4102324":[22,"伊豆の国市","中島"],"4102325":[22,"伊豆の国市","神島"],"4102400":[22,"伊豆市",""],"4102401":[22,"伊豆市","牧之郷"],"4102402":[22,"伊豆市","大野"],"4102403":[22,"伊豆市","年川"],"4102404":[22,"伊豆市","田代"],"4102405":[22,"伊豆市","加殿"],"4102406":[22,"伊豆市","日向"],"4102407":[22,"伊豆市","柏久保"],"4102411":[22,"伊豆市","熊坂"],"4102412":[22,"伊豆市","瓜生野"],"4102413":[22,"伊豆市","小立野"],"4102414":[22,"伊豆市","本立野"],"4102415":[22,"伊豆市","大平"],"4102416":[22,"伊豆市","修善寺"],"4102417":[22,"伊豆市","大沢"],"4102418":[22,"伊豆市","堀切"],"4102501":[22,"伊豆市","下白岩"],"4102502":[22,"伊豆市","上白岩"],"4102503":[22,"伊豆市","城"],"4102504":[22,"伊豆市","関野"],"4102505":[22,"伊豆市","八幡"],"4102506":[22,"伊豆市","徳永"],"4102507":[22,"伊豆市","冷川"],"4102508":[22,"伊豆市","柳瀬"],"4102509":[22,"伊豆市","梅木"],"4102511":[22,"伊豆市","宮上"],"4102512":[22,"伊豆市","中原戸"],"4102513":[22,"伊豆市","菅引"],"4102514":[22,"伊豆市","原保"],"4102515":[22,"伊豆市","地蔵堂"],"4102516":[22,"伊豆市","筏場"],"4102517":[22,"伊豆市","貴僧坊"],"4102518":[22,"伊豆市","姫之湯"],"4102519":[22,"伊豆市","戸倉野"],"4103201":[22,"伊豆市","佐野"],"4103202":[22,"伊豆市","雲金"],"4103203":[22,"伊豆市","矢熊"],"4103204":[22,"伊豆市","田沢"],"4103205":[22,"伊豆市","市山"],"4103206":[22,"伊豆市","湯ケ島"],"4103207":[22,"伊豆市","持越"],"4103208":[22,"伊豆市","吉奈"],"4103209":[22,"伊豆市","門野原"],"4103211":[22,"伊豆市","松ケ瀬"],"4103212":[22,"伊豆市","本柿木"],"4103213":[22,"伊豆市","青羽根"],"4103214":[22,"伊豆市","下船原"],"4103215":[22,"伊豆市","月ケ瀬"],"4103216":[22,"伊豆市","上船原"],"4103217":[22,"伊豆市","大平柿木"],"4103301":[22,"伊豆市","小土肥"],"4103302":[22,"伊豆市","土肥"],"4103303":[22,"伊豆市","八木沢"],"4103304":[22,"伊豆市","小下田"],"4103401":[22,"沼津市","井田"],"4103402":[22,"沼津市","戸田"],"4103500":[22,"賀茂郡西伊豆町",""],"4103501":[22,"賀茂郡西伊豆町","宇久須"],"4103502":[22,"賀茂郡西伊豆町","安良里"],"4103511":[22,"賀茂郡西伊豆町","大沢里"],"4103512":[22,"賀茂郡西伊豆町","一色"],"4103513":[22,"賀茂郡西伊豆町","中"],"4103514":[22,"賀茂郡西伊豆町","仁科"],"4103515":[22,"賀茂郡西伊豆町","田子"],"4103600":[22,"賀茂郡松崎町",""],"4103601":[22,"賀茂郡松崎町","池代"],"4103602":[22,"賀茂郡松崎町","小杉原"],"4103603":[22,"賀茂郡松崎町","明伏"],"4103604":[22,"賀茂郡松崎町","大沢"],"4103605":[22,"賀茂郡松崎町","峰輪"],"4103606":[22,"賀茂郡松崎町","船田"],"4103607":[22,"賀茂郡松崎町","門野"],"4103611":[22,"賀茂郡松崎町","松崎"],"4103612":[22,"賀茂郡松崎町","宮内"],"4103613":[22,"賀茂郡松崎町","岩科北側"],"4103614":[22,"賀茂郡松崎町","岩科南側"],"4103615":[22,"賀茂郡松崎町","雲見"],"4103616":[22,"賀茂郡松崎町","石部"],"4103617":[22,"賀茂郡松崎町","岩地"],"4103618":[22,"賀茂郡松崎町","道部"],"4103621":[22,"賀茂郡松崎町","吉田"],"4103622":[22,"賀茂郡松崎町","南郷"],"4103623":[22,"賀茂郡松崎町","伏倉"],"4103624":[22,"賀茂郡松崎町","江奈"],"4103625":[22,"賀茂郡松崎町","桜田"],"4103626":[22,"賀茂郡松崎町","那賀"],"4103627":[22,"賀茂郡松崎町","建久寺"],"4110000":[22,"三島市",""],"4110001":[22,"田方郡函南町","桑原"],"4110011":[22,"三島市","山中新田"],"4110012":[22,"三島市","笹原新田"],"4110013":[22,"三島市","三ツ谷新田"],"4110014":[22,"三島市","玉沢"],"4110015":[22,"三島市","市山新田"],"4110016":[22,"三島市","塚原新田"],"4110017":[22,"三島市","三恵台"],"4110018":[22,"三島市","初音台"],"4110019":[22,"三島市","松が丘"],"4110020":[22,"三島市","旭ケ丘"],"4110021":[22,"三島市","富士見台"],"4110022":[22,"三島市","川原ケ谷"],"4110023":[22,"三島市","加茂"],"4110024":[22,"三島市","若松町"],"4110025":[22,"三島市","壱町田"],"4110026":[22,"三島市","東壱町田"],"4110027":[22,"三島市","千枚原"],"4110028":[22,"三島市","富士ビレッジ"],"4110029":[22,"三島市","光ケ丘"],"4110030":[22,"三島市","西旭ケ丘町"],"4110031":[22,"三島市","幸原町"],"4110032":[22,"三島市","末広町"],"4110033":[22,"三島市","文教町"],"4110034":[22,"三島市","加茂川町"],"4110035":[22,"三島市","大宮町"],"4110036":[22,"三島市","一番町"],"4110037":[22,"三島市","泉町"],"4110038":[22,"三島市","西若町"],"4110039":[22,"三島市","寿町"],"4110041":[22,"三島市","佐野見晴台"],"4110042":[22,"三島市","平成台"],"4110043":[22,"三島市","沢地"],"4110044":[22,"三島市","徳倉"],"4110045":[22,"三島市","萩"],"4110046":[22,"三島市","芙蓉台"],"4110047":[22,"三島市","佐野"],"4110801":[22,"三島市","谷田"],"4110802":[22,"三島市","東大場"],"4110803":[22,"三島市","大場"],"4110804":[22,"三島市","多呂"],"4110805":[22,"三島市","北沢"],"4110806":[22,"三島市","柳郷地"],"4110807":[22,"三島市","竹倉"],"4110808":[22,"三島市","錦が丘"],"4110811":[22,"三島市","青木"],"4110812":[22,"三島市","藤代町"],"4110813":[22,"三島市","鶴喰"],"4110814":[22,"三島市","中島"],"4110815":[22,"三島市","安久"],"4110816":[22,"三島市","梅名"],"4110817":[22,"三島市","八反畑"],"4110821":[22,"三島市","平田"],"4110822":[22,"三島市","松本"],"4110823":[22,"三島市","御園"],"4110824":[22,"三島市","長伏"],"4110831":[22,"三島市","東本町"],"4110832":[22,"三島市","南二日町"],"4110833":[22,"三島市","中"],"4110834":[22,"三島市","新谷"],"4110835":[22,"三島市","玉川"],"4110836":[22,"三島市","富田町"],"4110837":[22,"三島市","南田町"],"4110838":[22,"三島市","中田町"],"4110841":[22,"三島市","南本町"],"4110842":[22,"三島市","南町"],"4110843":[22,"三島市","三好町"],"4110844":[22,"三島市","清住町"],"4110845":[22,"三島市","加屋町"],"4110846":[22,"三島市","栄町"],"4110847":[22,"三島市","西本町"],"4110848":[22,"三島市","緑町"],"4110851":[22,"三島市","日の出町"],"4110852":[22,"三島市","東町"],"4110853":[22,"三島市","大社町"],"4110854":[22,"三島市","北田町"],"4110855":[22,"三島市","本町"],"4110856":[22,"三島市","広小路町"],"4110857":[22,"三島市","芝本町"],"4110858":[22,"三島市","中央町"],"4110901":[22,"駿東郡清水町","新宿"],"4110902":[22,"駿東郡清水町","玉川"],"4110903":[22,"駿東郡清水町","堂庭"],"4110904":[22,"駿東郡清水町","柿田"],"4110905":[22,"駿東郡清水町","長沢"],"4110906":[22,"駿東郡清水町","八幡"],"4110907":[22,"駿東郡清水町","伏見"],"4110911":[22,"駿東郡清水町","久米田"],"4110912":[22,"駿東郡清水町","卸団地"],"4110913":[22,"駿東郡清水町","戸田"],"4110914":[22,"駿東郡清水町","畑中"],"4110915":[22,"駿東郡清水町","的場"],"4110916":[22,"駿東郡清水町","中徳倉"],"4110917":[22,"駿東郡清水町","徳倉"],"4110918":[22,"駿東郡清水町","湯川"],"4110931":[22,"駿東郡長泉町","東野"],"4110932":[22,"駿東郡長泉町","南一色"],"4110933":[22,"駿東郡長泉町","納米里"],"4110934":[22,"駿東郡長泉町","下長窪"],"4110935":[22,"駿東郡長泉町","上長窪"],"4110936":[22,"駿東郡長泉町","元長窪"],"4110941":[22,"駿東郡長泉町","上土狩"],"4110942":[22,"駿東郡長泉町","中土狩"],"4110943":[22,"駿東郡長泉町","下土狩"],"4110944":[22,"駿東郡長泉町","竹原"],"4110945":[22,"駿東郡長泉町","本宿"],"4110951":[22,"駿東郡長泉町","桜堤"],"4120000":[22,"御殿場市",""],"4120001":[22,"御殿場市","水土野"],"4120002":[22,"御殿場市","上小林"],"4120003":[22,"御殿場市","柴怒田"],"4120004":[22,"御殿場市","北久原"],"4120005":[22,"御殿場市","仁杉"],"4120006":[22,"御殿場市","中畑"],"4120007":[22,"御殿場市","永塚"],"4120008":[22,"御殿場市","印野"],"4120009":[22,"御殿場市","川柳"],"4120011":[22,"御殿場市","古沢"],"4120012":[22,"御殿場市","増田"],"4120013":[22,"御殿場市","小倉野"],"4120014":[22,"御殿場市","大堰"],"4120015":[22,"御殿場市","中丸"],"4120016":[22,"御殿場市","六日市場"],"4120017":[22,"御殿場市","塚原"],"4120018":[22,"御殿場市","山之尻"],"4120019":[22,"御殿場市","山尾田"],"4120021":[22,"御殿場市","二枚橋"],"4120022":[22,"御殿場市","清後"],"4120023":[22,"御殿場市","深沢"],"4120024":[22,"御殿場市","東山"],"4120025":[22,"御殿場市","二の岡"],"4120026":[22,"御殿場市","東田中"],"4120027":[22,"御殿場市","西田中"],"4120028":[22,"御殿場市","御殿場"],"4120029":[22,"御殿場市","神山平"],"4120031":[22,"御殿場市","沼田"],"4120032":[22,"御殿場市","二子"],"4120033":[22,"御殿場市","神山"],"4120034":[22,"御殿場市","大坂"],"4120035":[22,"御殿場市","中山"],"4120036":[22,"御殿場市","萩蕪"],"4120037":[22,"御殿場市","中清水"],"4120038":[22,"御殿場市","駒門"],"4120039":[22,"御殿場市","竈"],"4120041":[22,"御殿場市","茱萸沢"],"4120042":[22,"御殿場市","萩原"],"4120043":[22,"御殿場市","新橋"],"4120044":[22,"御殿場市","杉名沢"],"4120045":[22,"御殿場市","川島田"],"4120046":[22,"御殿場市","保土沢"],"4120047":[22,"御殿場市","神場"],"4120048":[22,"御殿場市","板妻"],"4120051":[22,"御殿場市","富士見原"],"4130000":[22,"熱海市",""],"4130001":[22,"熱海市","泉"],"4130002":[22,"熱海市","伊豆山"],"4130003":[22,"熱海市","海光町"],"4130004":[22,"熱海市","初島"],"4130005":[22,"熱海市","春日町"],"4130006":[22,"熱海市","桃山町"],"4130011":[22,"熱海市","田原本町"],"4130012":[22,"熱海市","東海岸町"],"4130013":[22,"熱海市","銀座町"],"4130014":[22,"熱海市","渚町"],"4130015":[22,"熱海市","中央町"],"4130016":[22,"熱海市","水口町"],"4130017":[22,"熱海市","福道町"],"4130018":[22,"熱海市","上宿町"],"4130019":[22,"熱海市","咲見町"],"4130021":[22,"熱海市","清水町"],"4130022":[22,"熱海市","昭和町"],"4130023":[22,"熱海市","和田浜南町"],"4130024":[22,"熱海市","和田町"],"4130025":[22,"熱海市","桜木町"],"4130026":[22,"熱海市","梅花町"],"4130027":[22,"熱海市","紅葉ガ丘町"],"4130028":[22,"熱海市","桜町"],"4130029":[22,"熱海市","小嵐町"],"4130031":[22,"熱海市","林ガ丘町"],"4130032":[22,"熱海市","梅園町"],"4130033":[22,"熱海市","熱海"],"4130034":[22,"熱海市","西山町"],"4130035":[22,"熱海市","緑ガ丘町"],"4130036":[22,"熱海市","日金町"],"4130037":[22,"熱海市","笹良ケ台町"],"4130038":[22,"熱海市","西熱海町"],"4130039":[22,"熱海市","相の原町"],"4130041":[22,"熱海市","青葉町"],"4130042":[22,"熱海市","山手町"],"4130101":[22,"熱海市","上多賀"],"4130102":[22,"熱海市","下多賀"],"4130103":[22,"熱海市","網代"],"4130111":[22,"伊東市","グリーンヒル別荘地"],"4130231":[22,"伊東市","富戸"],"4130232":[22,"伊東市","八幡野"],"4130233":[22,"伊東市","赤沢"],"4130234":[22,"伊東市","池"],"4130235":[22,"伊東市","大室高原"],"4130300":[22,"賀茂郡東伊豆町",""],"4130301":[22,"賀茂郡東伊豆町","大川"],"4130302":[22,"賀茂郡東伊豆町","奈良本"],"4130303":[22,"賀茂郡東伊豆町","片瀬"],"4130304":[22,"賀茂郡東伊豆町","白田"],"4130411":[22,"賀茂郡東伊豆町","稲取"],"4130500":[22,"賀茂郡河津町",""],"4130501":[22,"賀茂郡河津町","梨本"],"4130502":[22,"賀茂郡河津町","川津筏場"],"4130503":[22,"賀茂郡河津町","見高"],"4130504":[22,"賀茂郡河津町","田中"],"4130505":[22,"賀茂郡河津町","沢田"],"4130506":[22,"賀茂郡河津町","下佐ケ野"],"4130507":[22,"賀茂郡河津町","湯ケ野"],"4130508":[22,"賀茂郡河津町","小鍋"],"4130509":[22,"賀茂郡河津町","大鍋"],"4130511":[22,"賀茂郡河津町","峰"],"4130512":[22,"賀茂郡河津町","笹原"],"4130513":[22,"賀茂郡河津町","浜"],"4130514":[22,"賀茂郡河津町","縄地"],"4130515":[22,"賀茂郡河津町","谷津"],"4130516":[22,"賀茂郡河津町","逆川"],"4130701":[22,"下田市","落合"],"4130702":[22,"下田市","堀之内"],"4130703":[22,"下田市","荒増"],"4130704":[22,"下田市","椎原"],"4130705":[22,"下田市","箕作"],"4130711":[22,"下田市","相玉"],"4130712":[22,"下田市","横川"],"4130713":[22,"下田市","加増野"],"4130714":[22,"下田市","北湯ケ野"],"4130715":[22,"下田市","宇土金"],"4130716":[22,"下田市","須原"],"4140000":[22,"伊東市",""],"4140001":[22,"伊東市","宇佐美"],"4140002":[22,"伊東市","湯川"],"4140003":[22,"伊東市","中央町"],"4140004":[22,"伊東市","猪戸"],"4140005":[22,"伊東市","松原湯端町"],"4140006":[22,"伊東市","松原"],"4140011":[22,"伊東市","松川町"],"4140012":[22,"伊東市","宝町"],"4140013":[22,"伊東市","桜木町"],"4140014":[22,"伊東市","弥生町"],"4140015":[22,"伊東市","末広町"],"4140016":[22,"伊東市","岡広町"],"4140017":[22,"伊東市","幸町"],"4140018":[22,"伊東市","寿町"],"4140021":[22,"伊東市","松原本町"],"4140022":[22,"伊東市","東松原町"],"4140023":[22,"伊東市","渚町"],"4140024":[22,"伊東市","和田"],"4140025":[22,"伊東市","物見が丘"],"4140026":[22,"伊東市","竹の台"],"4140027":[22,"伊東市","竹の内"],"4140028":[22,"伊東市","銀座元町"],"4140031":[22,"伊東市","湯田町"],"4140032":[22,"伊東市","音無町"],"4140033":[22,"伊東市","馬場町"],"4140034":[22,"伊東市","瓶山"],"4140035":[22,"伊東市","南町"],"4140036":[22,"伊東市","宮川町"],"4140037":[22,"伊東市","桜ガ丘"],"4140038":[22,"伊東市","広野"],"4140041":[22,"伊東市","芝町"],"4140042":[22,"伊東市","静海町"],"4140043":[22,"伊東市","新井"],"4140044":[22,"伊東市","川奈"],"4140045":[22,"伊東市","玖須美元和田"],"4140046":[22,"伊東市","大原"],"4140051":[22,"伊東市","吉田"],"4140052":[22,"伊東市","十足"],"4140053":[22,"伊東市","荻"],"4140054":[22,"伊東市","鎌田"],"4140055":[22,"伊東市","岡"],"4150000":[22,"下田市",""],"4150001":[22,"下田市",""],"4150011":[22,"下田市","河内"],"4150012":[22,"下田市","白浜"],"4150013":[22,"下田市","柿崎"],"4150014":[22,"下田市","須崎"],"4150015":[22,"下田市","武ガ浜"],"4150016":[22,"下田市","中"],"4150017":[22,"下田市","東中"],"4150018":[22,"下田市","西中"],"4150021":[22,"下田市","一丁目"],"4150022":[22,"下田市","二丁目"],"4150023":[22,"下田市","三丁目"],"4150024":[22,"下田市","四丁目"],"4150025":[22,"下田市","五丁目"],"4150026":[22,"下田市","六丁目"],"4150027":[22,"下田市","旧岡方村"],"4150028":[22,"下田市","吉佐美"],"4150029":[22,"下田市","田牛"],"4150031":[22,"下田市","蓮台寺"],"4150032":[22,"下田市","立野"],"4150033":[22,"下田市","本郷"],"4150034":[22,"下田市","高馬"],"4150035":[22,"下田市","東本郷"],"4150036":[22,"下田市","西本郷"],"4150037":[22,"下田市","敷根"],"4150038":[22,"下田市","大賀茂"],"4150039":[22,"下田市","大沢"],"4150151":[22,"賀茂郡南伊豆町","青市"],"4150152":[22,"賀茂郡南伊豆町","湊"],"4150153":[22,"賀茂郡南伊豆町","手石"],"4150154":[22,"賀茂郡南伊豆町","下流"],"4150155":[22,"賀茂郡南伊豆町","大瀬"],"4150156":[22,"賀茂郡南伊豆町","石廊崎"],"4150300":[22,"賀茂郡南伊豆町",""],"4150301":[22,"賀茂郡南伊豆町","一條"],"4150302":[22,"賀茂郡南伊豆町","上賀茂"],"4150303":[22,"賀茂郡南伊豆町","下賀茂"],"4150304":[22,"賀茂郡南伊豆町","加納"],"4150305":[22,"賀茂郡南伊豆町","二條"],"4150306":[22,"賀茂郡南伊豆町","石井"],"4150311":[22,"賀茂郡南伊豆町","中木"],"4150312":[22,"賀茂郡南伊豆町","入間"],"4150313":[22,"賀茂郡南伊豆町","一色"],"4150314":[22,"賀茂郡南伊豆町","蝶ケ野"],"4150321":[22,"賀茂郡南伊豆町","毛倉野"],"4150322":[22,"賀茂郡南伊豆町","岩殿"],"4150323":[22,"賀茂郡南伊豆町","川合野"],"4150324":[22,"賀茂郡南伊豆町","上小野"],"4150325":[22,"賀茂郡南伊豆町","市之瀬"],"4150326":[22,"賀茂郡南伊豆町","蛇石"],"4150327":[22,"賀茂郡南伊豆町","青野"],"4150531":[22,"賀茂郡南伊豆町","一町田"],"4150532":[22,"賀茂郡南伊豆町","子浦"],"4150533":[22,"賀茂郡南伊豆町","立岩"],"4160901":[22,"富士市","岩本"],"4160902":[22,"富士市","長通"],"4160903":[22,"富士市","松本"],"4160904":[22,"富士市","本市場新田"],"4160905":[22,"富士市","五味島"],"4160906":[22,"富士市","本市場"],"4160907":[22,"富士市","中島"],"4160908":[22,"富士市","柚木"],"4160909":[22,"富士市","松岡"],"4160911":[22,"富士市","八幡町"],"4160912":[22,"富士市","加島町"],"4160913":[22,"富士市","平垣本町"],"4160914":[22,"富士市","本町"],"4160915":[22,"富士市","富士町"],"4160916":[22,"富士市","平垣"],"4160917":[22,"富士市","元町"],"4160918":[22,"富士市","平垣町"],"4160919":[22,"富士市","松富町"],"4160921":[22,"富士市","水戸島"],"4160922":[22,"富士市","水戸島元町"],"4160923":[22,"富士市","横割本町"],"4160924":[22,"富士市","水戸島本町"],"4160931":[22,"富士市","蓼原"],"4160932":[22,"富士市","柳島"],"4160933":[22,"富士市","中丸"],"4160934":[22,"富士市","鮫島"],"4160935":[22,"富士市","田子"],"4160936":[22,"富士市","中河原"],"4160937":[22,"富士市","前田"],"4160938":[22,"富士市","浜田町"],"4160939":[22,"富士市","川成島"],"4160941":[22,"富士市","十兵衛"],"4160942":[22,"富士市","上横割"],"4160943":[22,"富士市","下横割"],"4160944":[22,"富士市","横割"],"4160945":[22,"富士市","宮島"],"4160946":[22,"富士市","五貫島"],"4160947":[22,"富士市","宮下"],"4160948":[22,"富士市","森島"],"4160949":[22,"富士市","森下"],"4160951":[22,"富士市","米之宮町"],"4160952":[22,"富士市","青葉町"],"4160953":[22,"富士市","蓼原町"],"4160954":[22,"富士市","本市場町"],"4160955":[22,"富士市","川成新町"],"4170000":[22,"富士市",""],"4170001":[22,"富士市","今泉"],"4170002":[22,"富士市","依田橋"],"4170003":[22,"富士市","依田橋町"],"4170004":[22,"富士市","新橋町"],"4170011":[22,"富士市","鈴川本町"],"4170012":[22,"富士市","鈴川東町"],"4170013":[22,"富士市","鈴川中町"],"4170014":[22,"富士市","鈴川西町"],"4170015":[22,"富士市","鈴川町"],"4170021":[22,"富士市","依田原"],"4170022":[22,"富士市","依田原町"],"4170023":[22,"富士市","吉原宝町"],"4170024":[22,"富士市","八代町"],"4170025":[22,"富士市","瓜島"],"4170026":[22,"富士市","南町"],"4170031":[22,"富士市","田島"],"4170032":[22,"富士市","田島新田"],"4170033":[22,"富士市","島田町"],"4170034":[22,"富士市","津田"],"4170035":[22,"富士市","津田町"],"4170036":[22,"富士市","中河原"],"4170037":[22,"富士市","外木"],"4170041":[22,"富士市","御幸町"],"4170042":[22,"富士市","荒田島"],"4170043":[22,"富士市","荒田島町"],"4170044":[22,"富士市","高嶺町"],"4170045":[22,"富士市","錦町"],"4170046":[22,"富士市","青島"],"4170047":[22,"富士市","青島町"],"4170048":[22,"富士市","高島町"],"4170049":[22,"富士市","緑町"],"4170051":[22,"富士市","吉原"],"4170052":[22,"富士市","中央町"],"4170053":[22,"富士市","依田原新田"],"4170054":[22,"富士市","永田"],"4170055":[22,"富士市","永田町"],"4170056":[22,"富士市","日乃出町"],"4170057":[22,"富士市","瓜島町"],"4170058":[22,"富士市","永田北町"],"4170061":[22,"富士市","伝法"],"4170062":[22,"富士市","香西"],"4170063":[22,"富士市","香西新田"],"4170064":[22,"富士市","弥生"],"4170065":[22,"富士市","弥生新田"],"4170071":[22,"富士市","国久保"],"4170072":[22,"富士市","浅間上町"],"4170073":[22,"富士市","浅間本町"],"4170801":[22,"富士市","大淵"],"4170802":[22,"富士市","今宮"],"4170803":[22,"富士市","桑崎"],"4170804":[22,"富士市","石井"],"4170805":[22,"富士市","鵜無ケ淵"],"4170806":[22,"富士市","間門"],"4170807":[22,"富士市","神戸"],"4170808":[22,"富士市","一色"],"4170809":[22,"富士市","中野"],"4170811":[22,"富士市","江尾"],"4170812":[22,"富士市","境"],"4170813":[22,"富士市","船津"],"4170814":[22,"富士市","西船津"],"4170815":[22,"富士市","増川"],"4170816":[22,"富士市","増川新町"],"4170817":[22,"富士市","江尾南"],"4170821":[22,"富士市","神谷"],"4170822":[22,"富士市","神谷新町"],"4170823":[22,"富士市","神谷南"],"4170824":[22,"富士市","川尻東"],"4170825":[22,"富士市","川尻"],"4170826":[22,"富士市","中里"],"4170831":[22,"富士市","東柏原新田"],"4170832":[22,"富士市","中柏原新田"],"4170833":[22,"富士市","沼田新田"],"4170834":[22,"富士市","西柏原新田"],"4170835":[22,"富士市","柏原"],"4170841":[22,"富士市","富士岡"],"4170842":[22,"富士市","三新田"],"4170843":[22,"富士市","田中新田"],"4170844":[22,"富士市","檜新田"],"4170845":[22,"富士市","大野新田"],"4170846":[22,"富士市","今井"],"4170847":[22,"富士市","比奈"],"4170848":[22,"富士市","大野"],"4170851":[22,"富士市","富士見台"],"4170852":[22,"富士市","原田"],"4170853":[22,"富士市","宇東川東町"],"4170854":[22,"富士市","宇東川西町"],"4170855":[22,"富士市","三ツ沢"],"4170856":[22,"富士市","さんどまき"],"4170861":[22,"富士市","広見東本町"],"4170862":[22,"富士市","石坂"],"4170863":[22,"富士市","広見西本町"],"4170864":[22,"富士市","広見本町"],"4180000":[22,"富士宮市",""],"4180001":[22,"富士宮市","万野原新田"],"4180002":[22,"富士宮市","中原町"],"4180003":[22,"富士宮市","ひばりが丘"],"4180004":[22,"富士宮市","三園平"],"4180005":[22,"富士宮市","宮原"],"4180006":[22,"富士宮市","外神"],"4180007":[22,"富士宮市","外神東町"],"4180011":[22,"富士宮市","粟倉"],"4180012":[22,"富士宮市","村山"],"4180013":[22,"富士宮市","大岩"],"4180014":[22,"富士宮市","富士見ケ丘"],"4180015":[22,"富士宮市","舞々木町"],"4180016":[22,"富士宮市","阿幸地"],"4180017":[22,"富士宮市","舟久保町"],"4180018":[22,"富士宮市","粟倉南町"],"4180019":[22,"富士宮市","南陵"],"4180021":[22,"富士宮市","杉田"],"4180022":[22,"富士宮市","小泉"],"4180023":[22,"富士宮市","山本"],"4180024":[22,"富士宮市","貫戸"],"4180025":[22,"富士宮市","前田町"],"4180026":[22,"富士宮市","西小泉町"],"4180031":[22,"富士宮市","神田川町"],"4180032":[22,"富士宮市","浅間町"],"4180033":[22,"富士宮市","野中東町"],"4180034":[22,"富士宮市","黒田"],"4180035":[22,"富士宮市","星山"],"4180036":[22,"富士宮市","沼久保"],"4180037":[22,"富士宮市","安居山"],"4180038":[22,"富士宮市","野中町"],"4180039":[22,"富士宮市","野中"],"4180041":[22,"富士宮市","淀川町"],"4180042":[22,"富士宮市","貴船町"],"4180043":[22,"富士宮市","泉町"],"4180044":[22,"富士宮市","大中里"],"4180045":[22,"富士宮市","中島町"],"4180046":[22,"富士宮市","中里東町"],"4180047":[22,"富士宮市","青木"],"4180048":[22,"富士宮市","青木平"],"4180051":[22,"富士宮市","淀師"],"4180052":[22,"富士宮市","淀平町"],"4180053":[22,"富士宮市","宮北町"],"4180054":[22,"富士宮市","光町"],"4180055":[22,"富士宮市","宝町"],"4180056":[22,"富士宮市","西町"],"4180057":[22,"富士宮市","朝日町"],"4180058":[22,"富士宮市","穂波町"],"4180061":[22,"富士宮市","北町"],"4180062":[22,"富士宮市","城北町"],"4180063":[22,"富士宮市","若の宮町"],"4180064":[22,"富士宮市","元城町"],"4180065":[22,"富士宮市","中央町"],"4180066":[22,"富士宮市","大宮町"],"4180067":[22,"富士宮市","宮町"],"4180068":[22,"富士宮市","豊町"],"4180071":[22,"富士宮市","東阿幸地"],"4180072":[22,"富士宮市","矢立町"],"4180073":[22,"富士宮市","弓沢町"],"4180074":[22,"富士宮市","源道寺町"],"4180075":[22,"富士宮市","田中町"],"4180076":[22,"富士宮市","錦町"],"4180077":[22,"富士宮市","東町"],"4180078":[22,"富士宮市","阿幸地町"],"4180101":[22,"富士宮市","根原"],"4180102":[22,"富士宮市","人穴"],"4180103":[22,"富士宮市","上井出"],"4180104":[22,"富士宮市","内野"],"4180105":[22,"富士宮市","原"],"4180106":[22,"富士宮市","半野"],"4180107":[22,"富士宮市","佐折"],"4180108":[22,"富士宮市","猪之頭"],"4180109":[22,"富士宮市","麓"],"4180111":[22,"富士宮市","山宮"],"4180112":[22,"富士宮市","北山"],"4180113":[22,"富士宮市","馬見塚"],"4180114":[22,"富士宮市","下条"],"4180115":[22,"富士宮市","精進川"],"4180116":[22,"富士宮市","上条"],"4180117":[22,"富士宮市","狩宿"],"4190100":[22,"田方郡函南町",""],"4190101":[22,"田方郡函南町","桑原"],"4190102":[22,"田方郡函南町","田代"],"4190103":[22,"田方郡函南町","軽井沢"],"4190104":[22,"田方郡函南町","畑"],"4190105":[22,"田方郡函南町","丹那"],"4190106":[22,"田方郡函南町","南箱根ダイヤランド"],"4190107":[22,"田方郡函南町","平井"],"4190111":[22,"田方郡函南町","畑毛"],"4190112":[22,"田方郡函南町","柏谷"],"4190113":[22,"田方郡函南町","大土肥"],"4190114":[22,"田方郡函南町","仁田"],"4190115":[22,"田方郡函南町","新田"],"4190116":[22,"田方郡函南町","日守"],"4190121":[22,"田方郡函南町","大竹"],"4190122":[22,"田方郡函南町","上沢"],"4190123":[22,"田方郡函南町","間宮"],"4190124":[22,"田方郡函南町","塚本"],"4190125":[22,"田方郡函南町","肥田"],"4190201":[22,"富士市","厚原"],"4190202":[22,"富士市","久沢"],"4190203":[22,"富士市","鷹岡本町"],"4190204":[22,"富士市","入山瀬"],"4190205":[22,"富士市","天間"],"4190301":[22,"富士宮市","上柚野"],"4190302":[22,"富士宮市","猫沢"],"4190303":[22,"富士宮市","大鹿窪"],"4190304":[22,"富士宮市","鳥並"],"4190305":[22,"富士宮市","下柚野"],"4190311":[22,"富士宮市","上稲子"],"4190312":[22,"富士宮市","下稲子"],"4190313":[22,"富士宮市","西山"],"4190314":[22,"富士宮市","大久保"],"4190315":[22,"富士宮市","長貫"],"4190316":[22,"富士宮市","羽鮒"],"4190317":[22,"富士宮市","内房"]}